reconcile.py
reconciii-0.1.1.dist-info/METADATA
reconciii-0.1.1.dist-info/WHEEL
reconciii-0.1.1.dist-info/entry_points.txt
reconciii-0.1.1.dist-info/top_level.txt
reconciii-0.1.1.dist-info/RECORD
